{
  "updated_at": "2026-05-28T14:09:40.343102+00:00",
  "summary": {
    "total_videos_30d": 1459,
    "total_views_estimate": 150600,
    "success_rate": 65.7,
    "total_runs_sampled": 70,
    "failed_channels": [
      "Omni Mystery",
      "Я в Польше",
      "Smart Money"
    ],
    "warning_channels": []
  },
  "channels": [
    {
      "id": "omni-mystery",
      "name": "Omni Mystery",
      "emoji": "🔮",
      "repo": "Omni-Mystery-Machine",
      "repo_url": "https://github.com/RomanBazylev/Omni-Mystery-Machine",
      "youtube_url": "https://www.youtube.com/@VoidChronicles-AI",
      "workflows": {
        "run_bot.yml": {
          "name": "Run Bot",
          "schedule": "every 4h",
          "latest": {
            "id": 26571969272,
            "status": "completed",
            "conclusion": "success",
            "created_at": "2026-05-28T11:29:53Z",
            "updated_at": "2026-05-28T11:39:01Z",
            "html_url": "https://github.com/RomanBazylev/Omni-Mystery-Machine/actions/runs/26571969272",
            "run_number": 450
          },
          "failure_streak": 0,
          "recent_runs": [
            {
              "id": 26571969272,
              "status": "completed",
              "conclusion": "success",
              "created_at": "2026-05-28T11:29:53Z",
              "updated_at": "2026-05-28T11:39:01Z",
              "html_url": "https://github.com/RomanBazylev/Omni-Mystery-Machine/actions/runs/26571969272",
              "run_number": 450
            },
            {
              "id": 26561932721,
              "status": "completed",
              "conclusion": "success",
              "created_at": "2026-05-28T07:48:51Z",
              "updated_at": "2026-05-28T08:04:10Z",
              "html_url": "https://github.com/RomanBazylev/Omni-Mystery-Machine/actions/runs/26561932721",
              "run_number": 449
            },
            {
              "id": 26550434822,
              "status": "completed",
              "conclusion": "success",
              "created_at": "2026-05-28T02:13:21Z",
              "updated_at": "2026-05-28T02:20:53Z",
              "html_url": "https://github.com/RomanBazylev/Omni-Mystery-Machine/actions/runs/26550434822",
              "run_number": 448
            },
            {
              "id": 26540640782,
              "status": "completed",
              "conclusion": "success",
              "created_at": "2026-05-27T21:46:19Z",
              "updated_at": "2026-05-27T21:56:30Z",
              "html_url": "https://github.com/RomanBazylev/Omni-Mystery-Machine/actions/runs/26540640782",
              "run_number": 447
            },
            {
              "id": 26530197227,
              "status": "completed",
              "conclusion": "success",
              "created_at": "2026-05-27T18:19:47Z",
              "updated_at": "2026-05-27T18:27:47Z",
              "html_url": "https://github.com/RomanBazylev/Omni-Mystery-Machine/actions/runs/26530197227",
              "run_number": 446
            }
          ]
        },
        "generate_long_video.yml": {
          "name": "Generate Long Video",
          "schedule": "daily 09:00",
          "latest": {
            "id": 26574464511,
            "status": "completed",
            "conclusion": "failure",
            "created_at": "2026-05-28T12:24:30Z",
            "updated_at": "2026-05-28T12:25:51Z",
            "html_url": "https://github.com/RomanBazylev/Omni-Mystery-Machine/actions/runs/26574464511",
            "run_number": 79
          },
          "failure_streak": 5,
          "recent_runs": [
            {
              "id": 26574464511,
              "status": "completed",
              "conclusion": "failure",
              "created_at": "2026-05-28T12:24:30Z",
              "updated_at": "2026-05-28T12:25:51Z",
              "html_url": "https://github.com/RomanBazylev/Omni-Mystery-Machine/actions/runs/26574464511",
              "run_number": 79
            },
            {
              "id": 26510579233,
              "status": "completed",
              "conclusion": "failure",
              "created_at": "2026-05-27T12:17:53Z",
              "updated_at": "2026-05-27T12:19:56Z",
              "html_url": "https://github.com/RomanBazylev/Omni-Mystery-Machine/actions/runs/26510579233",
              "run_number": 78
            },
            {
              "id": 26400513036,
              "status": "completed",
              "conclusion": "failure",
              "created_at": "2026-05-25T12:28:29Z",
              "updated_at": "2026-05-25T12:29:55Z",
              "html_url": "https://github.com/RomanBazylev/Omni-Mystery-Machine/actions/runs/26400513036",
              "run_number": 77
            },
            {
              "id": 26359012370,
              "status": "completed",
              "conclusion": "failure",
              "created_at": "2026-05-24T10:40:21Z",
              "updated_at": "2026-05-24T10:41:40Z",
              "html_url": "https://github.com/RomanBazylev/Omni-Mystery-Machine/actions/runs/26359012370",
              "run_number": 76
            },
            {
              "id": 26330291004,
              "status": "completed",
              "conclusion": "failure",
              "created_at": "2026-05-23T10:24:50Z",
              "updated_at": "2026-05-23T10:26:26Z",
              "html_url": "https://github.com/RomanBazylev/Omni-Mystery-Machine/actions/runs/26330291004",
              "run_number": 75
            }
          ]
        }
      },
      "video_stats": {
        "total": 200,
        "last_30d": 178,
        "avg_views": 481,
        "avg_likes": 9,
        "avg_comments": 0,
        "best_video": {
          "title": "📡 The WOW Signal Still Can't Be Explained #Shorts",
          "video_id": "XwYHupZcbHc",
          "views": 1102
        },
        "last_upload": {
          "title": "🕳️ The Emptiest Place in Space Is Terrifying #Shorts",
          "video_id": "HWBo4uN7IyU",
          "uploaded_at": "2026-05-28T11:38:54.020805+00:00"
        },
        "last_short": {
          "title": "🕳️ The Emptiest Place in Space Is Terrifying #Shorts",
          "video_id": "HWBo4uN7IyU",
          "uploaded_at": "2026-05-28T11:38:54.020805+00:00"
        },
        "last_long": {
          "title": "CRISPR: Rewriting DNA 🧬",
          "video_id": "spgWNE7mNmo",
          "uploaded_at": "2026-05-02T10:02:59.473966+00:00"
        }
      }
    },
    {
      "id": "reddit-stories",
      "name": "Reddit Stories",
      "emoji": "📖",
      "repo": "youtube-reddit-stories",
      "repo_url": "https://github.com/RomanBazylev/youtube-reddit-stories",
      "youtube_url": "https://www.youtube.com/@told_in_secret",
      "workflows": {
        "generate_story_short.yml": {
          "name": "Generate Story Short",
          "schedule": "every 4h",
          "latest": {
            "id": 26572779556,
            "status": "completed",
            "conclusion": "success",
            "created_at": "2026-05-28T11:47:56Z",
            "updated_at": "2026-05-28T11:58:27Z",
            "html_url": "https://github.com/RomanBazylev/youtube-reddit-stories/actions/runs/26572779556",
            "run_number": 490
          },
          "failure_streak": 0,
          "recent_runs": [
            {
              "id": 26572779556,
              "status": "completed",
              "conclusion": "success",
              "created_at": "2026-05-28T11:47:56Z",
              "updated_at": "2026-05-28T11:58:27Z",
              "html_url": "https://github.com/RomanBazylev/youtube-reddit-stories/actions/runs/26572779556",
              "run_number": 490
            },
            {
              "id": 26562417151,
              "status": "completed",
              "conclusion": "success",
              "created_at": "2026-05-28T07:59:40Z",
              "updated_at": "2026-05-28T08:12:02Z",
              "html_url": "https://github.com/RomanBazylev/youtube-reddit-stories/actions/runs/26562417151",
              "run_number": 489
            },
            {
              "id": 26553313793,
              "status": "completed",
              "conclusion": "success",
              "created_at": "2026-05-28T03:42:46Z",
              "updated_at": "2026-05-28T03:54:40Z",
              "html_url": "https://github.com/RomanBazylev/youtube-reddit-stories/actions/runs/26553313793",
              "run_number": 488
            },
            {
              "id": 26541107257,
              "status": "completed",
              "conclusion": "success",
              "created_at": "2026-05-27T21:56:27Z",
              "updated_at": "2026-05-27T22:08:10Z",
              "html_url": "https://github.com/RomanBazylev/youtube-reddit-stories/actions/runs/26541107257",
              "run_number": 487
            },
            {
              "id": 26530557691,
              "status": "completed",
              "conclusion": "success",
              "created_at": "2026-05-27T18:26:39Z",
              "updated_at": "2026-05-27T18:38:49Z",
              "html_url": "https://github.com/RomanBazylev/youtube-reddit-stories/actions/runs/26530557691",
              "run_number": 486
            }
          ]
        },
        "generate_story_long.yml": {
          "name": "Generate Story Long",
          "schedule": "daily 07:00",
          "latest": {
            "id": 26569893368,
            "status": "completed",
            "conclusion": "success",
            "created_at": "2026-05-28T10:43:01Z",
            "updated_at": "2026-05-28T10:51:23Z",
            "html_url": "https://github.com/RomanBazylev/youtube-reddit-stories/actions/runs/26569893368",
            "run_number": 78
          },
          "failure_streak": 0,
          "recent_runs": [
            {
              "id": 26569893368,
              "status": "completed",
              "conclusion": "success",
              "created_at": "2026-05-28T10:43:01Z",
              "updated_at": "2026-05-28T10:51:23Z",
              "html_url": "https://github.com/RomanBazylev/youtube-reddit-stories/actions/runs/26569893368",
              "run_number": 78
            },
            {
              "id": 26506428264,
              "status": "completed",
              "conclusion": "failure",
              "created_at": "2026-05-27T10:44:40Z",
              "updated_at": "2026-05-27T11:04:33Z",
              "html_url": "https://github.com/RomanBazylev/youtube-reddit-stories/actions/runs/26506428264",
              "run_number": 77
            },
            {
              "id": 26447382385,
              "status": "completed",
              "conclusion": "failure",
              "created_at": "2026-05-26T10:39:34Z",
              "updated_at": "2026-05-26T10:59:54Z",
              "html_url": "https://github.com/RomanBazylev/youtube-reddit-stories/actions/runs/26447382385",
              "run_number": 76
            },
            {
              "id": 26397187499,
              "status": "completed",
              "conclusion": "failure",
              "created_at": "2026-05-25T11:02:59Z",
              "updated_at": "2026-05-25T11:22:46Z",
              "html_url": "https://github.com/RomanBazylev/youtube-reddit-stories/actions/runs/26397187499",
              "run_number": 75
            },
            {
              "id": 26357251267,
              "status": "completed",
              "conclusion": "failure",
              "created_at": "2026-05-24T09:12:31Z",
              "updated_at": "2026-05-24T09:32:26Z",
              "html_url": "https://github.com/RomanBazylev/youtube-reddit-stories/actions/runs/26357251267",
              "run_number": 74
            }
          ]
        }
      },
      "video_stats": {
        "total": 200,
        "last_30d": 177,
        "avg_views": 0,
        "avg_likes": 0,
        "avg_comments": 0,
        "best_video": null,
        "last_upload": {
          "title": "My Kid's Drawing Almost Got Me Investigated 🔥 #shorts",
          "video_id": "lObfO-0Y16U",
          "uploaded_at": "2026-05-28T11:58:21.768299+00:00"
        },
        "last_short": {
          "title": "My Kid's Drawing Almost Got Me Investigated 🔥 #shorts",
          "video_id": "lObfO-0Y16U",
          "uploaded_at": "2026-05-28T11:58:21.768299+00:00"
        },
        "last_long": {
          "title": "5 Insane Reddit Stories 🤯",
          "video_id": "zkWNXycpri0",
          "uploaded_at": "2026-05-28T10:51:18.897502+00:00"
        }
      }
    },
    {
      "id": "poland",
      "name": "Я в Польше",
      "emoji": "🇵🇱",
      "repo": "youtube-poland-automation",
      "repo_url": "https://github.com/RomanBazylev/youtube-poland-automation",
      "youtube_url": "https://www.youtube.com/@i_in_poland",
      "workflows": {
        "generate_poland_short.yml": {
          "name": "Generate Poland Short",
          "schedule": "every 4h",
          "latest": {
            "id": 26571924112,
            "status": "completed",
            "conclusion": "success",
            "created_at": "2026-05-28T11:28:50Z",
            "updated_at": "2026-05-28T11:36:54Z",
            "html_url": "https://github.com/RomanBazylev/youtube-poland-automation/actions/runs/26571924112",
            "run_number": 486
          },
          "failure_streak": 0,
          "recent_runs": [
            {
              "id": 26571924112,
              "status": "completed",
              "conclusion": "success",
              "created_at": "2026-05-28T11:28:50Z",
              "updated_at": "2026-05-28T11:36:54Z",
              "html_url": "https://github.com/RomanBazylev/youtube-poland-automation/actions/runs/26571924112",
              "run_number": 486
            },
            {
              "id": 26561845764,
              "status": "completed",
              "conclusion": "success",
              "created_at": "2026-05-28T07:46:54Z",
              "updated_at": "2026-05-28T07:55:46Z",
              "html_url": "https://github.com/RomanBazylev/youtube-poland-automation/actions/runs/26561845764",
              "run_number": 485
            },
            {
              "id": 26550175916,
              "status": "completed",
              "conclusion": "success",
              "created_at": "2026-05-28T02:04:48Z",
              "updated_at": "2026-05-28T02:16:32Z",
              "html_url": "https://github.com/RomanBazylev/youtube-poland-automation/actions/runs/26550175916",
              "run_number": 484
            },
            {
              "id": 26540602705,
              "status": "completed",
              "conclusion": "success",
              "created_at": "2026-05-27T21:45:32Z",
              "updated_at": "2026-05-27T21:58:53Z",
              "html_url": "https://github.com/RomanBazylev/youtube-poland-automation/actions/runs/26540602705",
              "run_number": 483
            },
            {
              "id": 26530152656,
              "status": "completed",
              "conclusion": "success",
              "created_at": "2026-05-27T18:19:00Z",
              "updated_at": "2026-05-27T18:28:00Z",
              "html_url": "https://github.com/RomanBazylev/youtube-poland-automation/actions/runs/26530152656",
              "run_number": 482
            }
          ]
        },
        "generate_poland_long.yml": {
          "name": "Generate Poland Long",
          "schedule": "2x daily",
          "latest": {
            "id": 26569973184,
            "status": "completed",
            "conclusion": "failure",
            "created_at": "2026-05-28T10:44:51Z",
            "updated_at": "2026-05-28T10:54:56Z",
            "html_url": "https://github.com/RomanBazylev/youtube-poland-automation/actions/runs/26569973184",
            "run_number": 145
          },
          "failure_streak": 3,
          "recent_runs": [
            {
              "id": 26569973184,
              "status": "completed",
              "conclusion": "failure",
              "created_at": "2026-05-28T10:44:51Z",
              "updated_at": "2026-05-28T10:54:56Z",
              "html_url": "https://github.com/RomanBazylev/youtube-poland-automation/actions/runs/26569973184",
              "run_number": 145
            },
            {
              "id": 26530338854,
              "status": "completed",
              "conclusion": "failure",
              "created_at": "2026-05-27T18:22:25Z",
              "updated_at": "2026-05-27T18:27:47Z",
              "html_url": "https://github.com/RomanBazylev/youtube-poland-automation/actions/runs/26530338854",
              "run_number": 144
            },
            {
              "id": 26506616750,
              "status": "completed",
              "conclusion": "failure",
              "created_at": "2026-05-27T10:48:53Z",
              "updated_at": "2026-05-27T10:59:19Z",
              "html_url": "https://github.com/RomanBazylev/youtube-poland-automation/actions/runs/26506616750",
              "run_number": 143
            },
            {
              "id": 26466960202,
              "status": "completed",
              "conclusion": "success",
              "created_at": "2026-05-26T18:22:21Z",
              "updated_at": "2026-05-26T18:31:50Z",
              "html_url": "https://github.com/RomanBazylev/youtube-poland-automation/actions/runs/26466960202",
              "run_number": 142
            },
            {
              "id": 26412744074,
              "status": "completed",
              "conclusion": "failure",
              "created_at": "2026-05-25T17:39:14Z",
              "updated_at": "2026-05-25T17:41:52Z",
              "html_url": "https://github.com/RomanBazylev/youtube-poland-automation/actions/runs/26412744074",
              "run_number": 141
            }
          ]
        }
      },
      "video_stats": {
        "total": 200,
        "last_30d": 177,
        "avg_views": 0,
        "avg_likes": 0,
        "avg_comments": 0,
        "best_video": null,
        "last_upload": {
          "title": "Торунь: Коперник и пряники 🇵🇱 #shorts",
          "video_id": "WL8SETCFQZ0",
          "uploaded_at": "2026-05-28T11:36:50.452257+00:00"
        },
        "last_short": {
          "title": "Торунь: Коперник и пряники 🇵🇱 #shorts",
          "video_id": "WL8SETCFQZ0",
          "uploaded_at": "2026-05-28T11:36:50.452257+00:00"
        },
        "last_long": {
          "title": "Бесплодие в Польше 🇵🇱",
          "video_id": "55vB7caeloQ",
          "uploaded_at": "2026-05-26T18:31:44.448126+00:00"
        }
      }
    },
    {
      "id": "salesforce",
      "name": "Salesforce Tips",
      "emoji": "⚡",
      "repo": "youtube-salesforce-automation",
      "repo_url": "https://github.com/RomanBazylev/youtube-salesforce-automation",
      "youtube_url": "https://www.youtube.com/@SalesforceRaman",
      "workflows": {
        "generate_salesforce_short.yml": {
          "name": "Generate Salesforce Short",
          "schedule": "every 4h",
          "latest": {
            "id": 26571769481,
            "status": "completed",
            "conclusion": "success",
            "created_at": "2026-05-28T11:25:18Z",
            "updated_at": "2026-05-28T11:32:47Z",
            "html_url": "https://github.com/RomanBazylev/youtube-salesforce-automation/actions/runs/26571769481",
            "run_number": 484
          },
          "failure_streak": 0,
          "recent_runs": [
            {
              "id": 26571769481,
              "status": "completed",
              "conclusion": "success",
              "created_at": "2026-05-28T11:25:18Z",
              "updated_at": "2026-05-28T11:32:47Z",
              "html_url": "https://github.com/RomanBazylev/youtube-salesforce-automation/actions/runs/26571769481",
              "run_number": 484
            },
            {
              "id": 26561731720,
              "status": "completed",
              "conclusion": "success",
              "created_at": "2026-05-28T07:44:21Z",
              "updated_at": "2026-05-28T07:55:35Z",
              "html_url": "https://github.com/RomanBazylev/youtube-salesforce-automation/actions/runs/26561731720",
              "run_number": 483
            },
            {
              "id": 26549036973,
              "status": "completed",
              "conclusion": "success",
              "created_at": "2026-05-28T01:29:20Z",
              "updated_at": "2026-05-28T01:37:48Z",
              "html_url": "https://github.com/RomanBazylev/youtube-salesforce-automation/actions/runs/26549036973",
              "run_number": 482
            },
            {
              "id": 26539895701,
              "status": "completed",
              "conclusion": "success",
              "created_at": "2026-05-27T21:30:27Z",
              "updated_at": "2026-05-27T21:39:18Z",
              "html_url": "https://github.com/RomanBazylev/youtube-salesforce-automation/actions/runs/26539895701",
              "run_number": 481
            },
            {
              "id": 26529937946,
              "status": "completed",
              "conclusion": "success",
              "created_at": "2026-05-27T18:14:52Z",
              "updated_at": "2026-05-27T18:23:32Z",
              "html_url": "https://github.com/RomanBazylev/youtube-salesforce-automation/actions/runs/26529937946",
              "run_number": 480
            }
          ]
        },
        "generate_salesforce_long.yml": {
          "name": "Generate Salesforce Long",
          "schedule": "daily 08:00",
          "latest": {
            "id": 26572436455,
            "status": "completed",
            "conclusion": "cancelled",
            "created_at": "2026-05-28T11:40:20Z",
            "updated_at": "2026-05-28T12:40:40Z",
            "html_url": "https://github.com/RomanBazylev/youtube-salesforce-automation/actions/runs/26572436455",
            "run_number": 41
          },
          "failure_streak": 0,
          "recent_runs": [
            {
              "id": 26572436455,
              "status": "completed",
              "conclusion": "cancelled",
              "created_at": "2026-05-28T11:40:20Z",
              "updated_at": "2026-05-28T12:40:40Z",
              "html_url": "https://github.com/RomanBazylev/youtube-salesforce-automation/actions/runs/26572436455",
              "run_number": 41
            },
            {
              "id": 26508980061,
              "status": "completed",
              "conclusion": "cancelled",
              "created_at": "2026-05-27T11:41:03Z",
              "updated_at": "2026-05-27T12:41:25Z",
              "html_url": "https://github.com/RomanBazylev/youtube-salesforce-automation/actions/runs/26508980061",
              "run_number": 40
            },
            {
              "id": 26399179953,
              "status": "completed",
              "conclusion": "cancelled",
              "created_at": "2026-05-25T11:54:44Z",
              "updated_at": "2026-05-25T12:55:04Z",
              "html_url": "https://github.com/RomanBazylev/youtube-salesforce-automation/actions/runs/26399179953",
              "run_number": 39
            },
            {
              "id": 26358162587,
              "status": "completed",
              "conclusion": "cancelled",
              "created_at": "2026-05-24T09:57:31Z",
              "updated_at": "2026-05-24T10:57:52Z",
              "html_url": "https://github.com/RomanBazylev/youtube-salesforce-automation/actions/runs/26358162587",
              "run_number": 38
            },
            {
              "id": 26329768275,
              "status": "completed",
              "conclusion": "cancelled",
              "created_at": "2026-05-23T09:56:15Z",
              "updated_at": "2026-05-23T10:56:34Z",
              "html_url": "https://github.com/RomanBazylev/youtube-salesforce-automation/actions/runs/26329768275",
              "run_number": 37
            }
          ]
        }
      },
      "video_stats": {
        "total": 200,
        "last_30d": 170,
        "avg_views": 0,
        "avg_likes": 0,
        "avg_comments": 0,
        "best_video": null,
        "last_upload": {
          "title": "GetFeedback Ends: 3 Alternatives 🚀 #shorts #salesforce",
          "video_id": "RS_RmL6U9Dw",
          "uploaded_at": "2026-05-28T11:32:43.484101+00:00"
        },
        "last_short": {
          "title": "GetFeedback Ends: 3 Alternatives 🚀 #shorts #salesforce",
          "video_id": "RS_RmL6U9Dw",
          "uploaded_at": "2026-05-28T11:32:43.484101+00:00"
        },
        "last_long": null
      }
    },
    {
      "id": "money",
      "name": "Smart Money",
      "emoji": "💰",
      "repo": "youtube-smart-money-tips",
      "repo_url": "https://github.com/RomanBazylev/youtube-smart-money-tips",
      "youtube_url": "https://www.youtube.com/@BestSmartMoneyTips",
      "workflows": {
        "generate_money_short.yml": {
          "name": "Generate Money Short",
          "schedule": "every 3h",
          "latest": {
            "id": 26574479080,
            "status": "completed",
            "conclusion": "failure",
            "created_at": "2026-05-28T12:24:48Z",
            "updated_at": "2026-05-28T12:25:27Z",
            "html_url": "https://github.com/RomanBazylev/youtube-smart-money-tips/actions/runs/26574479080",
            "run_number": 582
          },
          "failure_streak": 1,
          "recent_runs": [
            {
              "id": 26574479080,
              "status": "completed",
              "conclusion": "failure",
              "created_at": "2026-05-28T12:24:48Z",
              "updated_at": "2026-05-28T12:25:27Z",
              "html_url": "https://github.com/RomanBazylev/youtube-smart-money-tips/actions/runs/26574479080",
              "run_number": 582
            },
            {
              "id": 26559843796,
              "status": "completed",
              "conclusion": "success",
              "created_at": "2026-05-28T06:59:18Z",
              "updated_at": "2026-05-28T07:09:54Z",
              "html_url": "https://github.com/RomanBazylev/youtube-smart-money-tips/actions/runs/26559843796",
              "run_number": 581
            },
            {
              "id": 26551880253,
              "status": "completed",
              "conclusion": "success",
              "created_at": "2026-05-28T02:58:28Z",
              "updated_at": "2026-05-28T03:09:19Z",
              "html_url": "https://github.com/RomanBazylev/youtube-smart-money-tips/actions/runs/26551880253",
              "run_number": 580
            },
            {
              "id": 26542950474,
              "status": "completed",
              "conclusion": "success",
              "created_at": "2026-05-27T22:39:35Z",
              "updated_at": "2026-05-27T22:54:55Z",
              "html_url": "https://github.com/RomanBazylev/youtube-smart-money-tips/actions/runs/26542950474",
              "run_number": 579
            },
            {
              "id": 26536065437,
              "status": "completed",
              "conclusion": "success",
              "created_at": "2026-05-27T20:13:02Z",
              "updated_at": "2026-05-27T20:32:11Z",
              "html_url": "https://github.com/RomanBazylev/youtube-smart-money-tips/actions/runs/26536065437",
              "run_number": 578
            }
          ]
        },
        "generate_money_long.yml": {
          "name": "Generate Money Long",
          "schedule": "daily 09:00",
          "latest": {
            "id": 26574474666,
            "status": "completed",
            "conclusion": "failure",
            "created_at": "2026-05-28T12:24:43Z",
            "updated_at": "2026-05-28T12:32:53Z",
            "html_url": "https://github.com/RomanBazylev/youtube-smart-money-tips/actions/runs/26574474666",
            "run_number": 68
          },
          "failure_streak": 5,
          "recent_runs": [
            {
              "id": 26574474666,
              "status": "completed",
              "conclusion": "failure",
              "created_at": "2026-05-28T12:24:43Z",
              "updated_at": "2026-05-28T12:32:53Z",
              "html_url": "https://github.com/RomanBazylev/youtube-smart-money-tips/actions/runs/26574474666",
              "run_number": 68
            },
            {
              "id": 26510603221,
              "status": "completed",
              "conclusion": "failure",
              "created_at": "2026-05-27T12:18:22Z",
              "updated_at": "2026-05-27T12:26:38Z",
              "html_url": "https://github.com/RomanBazylev/youtube-smart-money-tips/actions/runs/26510603221",
              "run_number": 67
            },
            {
              "id": 26400522911,
              "status": "completed",
              "conclusion": "failure",
              "created_at": "2026-05-25T12:28:44Z",
              "updated_at": "2026-05-25T12:36:43Z",
              "html_url": "https://github.com/RomanBazylev/youtube-smart-money-tips/actions/runs/26400522911",
              "run_number": 66
            },
            {
              "id": 26359017377,
              "status": "completed",
              "conclusion": "failure",
              "created_at": "2026-05-24T10:40:36Z",
              "updated_at": "2026-05-24T10:48:15Z",
              "html_url": "https://github.com/RomanBazylev/youtube-smart-money-tips/actions/runs/26359017377",
              "run_number": 65
            },
            {
              "id": 26330293244,
              "status": "completed",
              "conclusion": "failure",
              "created_at": "2026-05-23T10:24:57Z",
              "updated_at": "2026-05-23T10:32:18Z",
              "html_url": "https://github.com/RomanBazylev/youtube-smart-money-tips/actions/runs/26330293244",
              "run_number": 64
            }
          ]
        }
      },
      "video_stats": {
        "total": 200,
        "last_30d": 185,
        "avg_views": 42,
        "avg_likes": 0,
        "avg_comments": 0,
        "best_video": {
          "title": "💸 Tax Hack: $3,459/year #shorts #money",
          "video_id": "FO5HtKJUw5w",
          "views": 267
        },
        "last_upload": {
          "title": "Tax Optimization 📊 #shorts #money",
          "video_id": "motFEn394Es",
          "uploaded_at": "2026-05-28T07:09:49.670962+00:00"
        },
        "last_short": {
          "title": "Tax Optimization 📊 #shorts #money",
          "video_id": "motFEn394Es",
          "uploaded_at": "2026-05-28T07:09:49.670962+00:00"
        },
        "last_long": null
      }
    },
    {
      "id": "ironman",
      "name": "Iron Man",
      "emoji": "🦾",
      "repo": "youtube-ironman-automation",
      "repo_url": "https://github.com/RomanBazylev/youtube-ironman-automation",
      "youtube_url": "https://www.youtube.com/@IronMind_Unbreakable",
      "workflows": {
        "generate_video.yml": {
          "name": "Generate Video",
          "schedule": "every 3h",
          "latest": {
            "id": 26568209503,
            "status": "completed",
            "conclusion": "success",
            "created_at": "2026-05-28T10:05:03Z",
            "updated_at": "2026-05-28T10:07:31Z",
            "html_url": "https://github.com/RomanBazylev/youtube-ironman-automation/actions/runs/26568209503",
            "run_number": 597
          },
          "failure_streak": 0,
          "recent_runs": [
            {
              "id": 26568209503,
              "status": "completed",
              "conclusion": "success",
              "created_at": "2026-05-28T10:05:03Z",
              "updated_at": "2026-05-28T10:07:31Z",
              "html_url": "https://github.com/RomanBazylev/youtube-ironman-automation/actions/runs/26568209503",
              "run_number": 597
            },
            {
              "id": 26553510065,
              "status": "completed",
              "conclusion": "success",
              "created_at": "2026-05-28T03:49:03Z",
              "updated_at": "2026-05-28T03:51:28Z",
              "html_url": "https://github.com/RomanBazylev/youtube-ironman-automation/actions/runs/26553510065",
              "run_number": 596
            },
            {
              "id": 26543033751,
              "status": "completed",
              "conclusion": "success",
              "created_at": "2026-05-27T22:41:37Z",
              "updated_at": "2026-05-27T22:44:26Z",
              "html_url": "https://github.com/RomanBazylev/youtube-ironman-automation/actions/runs/26543033751",
              "run_number": 595
            },
            {
              "id": 26536434757,
              "status": "completed",
              "conclusion": "success",
              "created_at": "2026-05-27T20:20:19Z",
              "updated_at": "2026-05-27T20:22:30Z",
              "html_url": "https://github.com/RomanBazylev/youtube-ironman-automation/actions/runs/26536434757",
              "run_number": 594
            },
            {
              "id": 26522182828,
              "status": "completed",
              "conclusion": "success",
              "created_at": "2026-05-27T15:49:02Z",
              "updated_at": "2026-05-27T15:51:37Z",
              "html_url": "https://github.com/RomanBazylev/youtube-ironman-automation/actions/runs/26522182828",
              "run_number": 593
            }
          ]
        },
        "generate_longform.yml": {
          "name": "Generate Longform",
          "schedule": "Mon/Wed/Fri 06:00",
          "latest": {
            "id": 26504577643,
            "status": "completed",
            "conclusion": "success",
            "created_at": "2026-05-27T10:03:40Z",
            "updated_at": "2026-05-27T10:05:59Z",
            "html_url": "https://github.com/RomanBazylev/youtube-ironman-automation/actions/runs/26504577643",
            "run_number": 36
          },
          "failure_streak": 0,
          "recent_runs": [
            {
              "id": 26504577643,
              "status": "completed",
              "conclusion": "success",
              "created_at": "2026-05-27T10:03:40Z",
              "updated_at": "2026-05-27T10:05:59Z",
              "html_url": "https://github.com/RomanBazylev/youtube-ironman-automation/actions/runs/26504577643",
              "run_number": 36
            },
            {
              "id": 26395496371,
              "status": "completed",
              "conclusion": "success",
              "created_at": "2026-05-25T10:19:19Z",
              "updated_at": "2026-05-25T10:21:43Z",
              "html_url": "https://github.com/RomanBazylev/youtube-ironman-automation/actions/runs/26395496371",
              "run_number": 35
            },
            {
              "id": 26280280974,
              "status": "completed",
              "conclusion": "success",
              "created_at": "2026-05-22T09:37:41Z",
              "updated_at": "2026-05-22T09:40:00Z",
              "html_url": "https://github.com/RomanBazylev/youtube-ironman-automation/actions/runs/26280280974",
              "run_number": 34
            },
            {
              "id": 26154605084,
              "status": "completed",
              "conclusion": "success",
              "created_at": "2026-05-20T09:44:21Z",
              "updated_at": "2026-05-20T09:55:09Z",
              "html_url": "https://github.com/RomanBazylev/youtube-ironman-automation/actions/runs/26154605084",
              "run_number": 33
            },
            {
              "id": 26027322524,
              "status": "completed",
              "conclusion": "success",
              "created_at": "2026-05-18T10:15:08Z",
              "updated_at": "2026-05-18T10:17:48Z",
              "html_url": "https://github.com/RomanBazylev/youtube-ironman-automation/actions/runs/26027322524",
              "run_number": 32
            }
          ]
        }
      },
      "video_stats": {
        "total": 200,
        "last_30d": 200,
        "avg_views": 229,
        "avg_likes": 4,
        "avg_comments": 0,
        "best_video": {
          "title": "7 Brutal Truths Weak Men Avoid",
          "video_id": "Hd9ubvEjp54",
          "views": 1224
        },
        "last_upload": {
          "title": "7 Brutal Truths Weak Men Avoid",
          "video_id": "W_Uf7M_mkRU",
          "uploaded_at": "2026-05-28T10:07:00.151818+00:00"
        },
        "last_short": null,
        "last_long": {
          "title": "7 Brutal Truths Weak Men Avoid",
          "video_id": "W_Uf7M_mkRU",
          "uploaded_at": "2026-05-28T10:07:00.151818+00:00"
        }
      }
    },
    {
      "id": "fishing",
      "name": "Рыбалка",
      "emoji": "🎣",
      "repo": "youtube-fishing-automation",
      "repo_url": "https://github.com/RomanBazylev/youtube-fishing-automation",
      "youtube_url": "https://www.youtube.com/@rybak-Artsiom",
      "workflows": {
        "generate_fishing_short.yml": {
          "name": "Generate Fishing Short",
          "schedule": "every 4h",
          "latest": {
            "id": 26571769302,
            "status": "completed",
            "conclusion": "success",
            "created_at": "2026-05-28T11:25:18Z",
            "updated_at": "2026-05-28T11:34:09Z",
            "html_url": "https://github.com/RomanBazylev/youtube-fishing-automation/actions/runs/26571769302",
            "run_number": 497
          },
          "failure_streak": 0,
          "recent_runs": [
            {
              "id": 26571769302,
              "status": "completed",
              "conclusion": "success",
              "created_at": "2026-05-28T11:25:18Z",
              "updated_at": "2026-05-28T11:34:09Z",
              "html_url": "https://github.com/RomanBazylev/youtube-fishing-automation/actions/runs/26571769302",
              "run_number": 497
            },
            {
              "id": 26561735011,
              "status": "completed",
              "conclusion": "success",
              "created_at": "2026-05-28T07:44:25Z",
              "updated_at": "2026-05-28T07:53:10Z",
              "html_url": "https://github.com/RomanBazylev/youtube-fishing-automation/actions/runs/26561735011",
              "run_number": 496
            },
            {
              "id": 26549013206,
              "status": "completed",
              "conclusion": "success",
              "created_at": "2026-05-28T01:28:38Z",
              "updated_at": "2026-05-28T01:38:15Z",
              "html_url": "https://github.com/RomanBazylev/youtube-fishing-automation/actions/runs/26549013206",
              "run_number": 495
            },
            {
              "id": 26539869472,
              "status": "completed",
              "conclusion": "success",
              "created_at": "2026-05-27T21:29:56Z",
              "updated_at": "2026-05-27T21:38:16Z",
              "html_url": "https://github.com/RomanBazylev/youtube-fishing-automation/actions/runs/26539869472",
              "run_number": 494
            },
            {
              "id": 26529931599,
              "status": "completed",
              "conclusion": "success",
              "created_at": "2026-05-27T18:14:44Z",
              "updated_at": "2026-05-27T18:23:28Z",
              "html_url": "https://github.com/RomanBazylev/youtube-fishing-automation/actions/runs/26529931599",
              "run_number": 493
            }
          ]
        }
      },
      "video_stats": {
        "total": 200,
        "last_30d": 172,
        "avg_views": 0,
        "avg_likes": 0,
        "avg_comments": 0,
        "best_video": null,
        "last_upload": {
          "title": "Борьба с акулой 5 часов! #shorts",
          "video_id": "g6XFy4wB_Tw",
          "uploaded_at": "2026-05-28T11:34:04.247751+00:00"
        },
        "last_short": {
          "title": "Борьба с акулой 5 часов! #shorts",
          "video_id": "g6XFy4wB_Tw",
          "uploaded_at": "2026-05-28T11:34:04.247751+00:00"
        },
        "last_long": null
      }
    },
    {
      "id": "hard4fun",
      "name": "GlitchRealityAI",
      "emoji": "👾",
      "repo": "hard4fun",
      "repo_url": "https://github.com/RomanBazylev/hard4fun",
      "youtube_url": "https://www.youtube.com/@hard4fun",
      "workflows": {
        "daily-shorts.yml": {
          "name": "Daily-Shorts",
          "schedule": "2x daily (00:00 + 14:00 UTC)",
          "latest": {
            "id": 26553366475,
            "status": "completed",
            "conclusion": "success",
            "created_at": "2026-05-28T03:44:25Z",
            "updated_at": "2026-05-28T03:55:21Z",
            "html_url": "https://github.com/RomanBazylev/hard4fun/actions/runs/26553366475",
            "run_number": 145
          },
          "failure_streak": 0,
          "recent_runs": [
            {
              "id": 26553366475,
              "status": "completed",
              "conclusion": "success",
              "created_at": "2026-05-28T03:44:25Z",
              "updated_at": "2026-05-28T03:55:21Z",
              "html_url": "https://github.com/RomanBazylev/hard4fun/actions/runs/26553366475",
              "run_number": 145
            },
            {
              "id": 26525828748,
              "status": "completed",
              "conclusion": "success",
              "created_at": "2026-05-27T16:56:17Z",
              "updated_at": "2026-05-27T17:07:36Z",
              "html_url": "https://github.com/RomanBazylev/hard4fun/actions/runs/26525828748",
              "run_number": 144
            },
            {
              "id": 26489831800,
              "status": "completed",
              "conclusion": "success",
              "created_at": "2026-05-27T03:57:20Z",
              "updated_at": "2026-05-27T04:07:56Z",
              "html_url": "https://github.com/RomanBazylev/hard4fun/actions/runs/26489831800",
              "run_number": 143
            },
            {
              "id": 26463686066,
              "status": "completed",
              "conclusion": "success",
              "created_at": "2026-05-26T17:17:11Z",
              "updated_at": "2026-05-26T17:27:37Z",
              "html_url": "https://github.com/RomanBazylev/hard4fun/actions/runs/26463686066",
              "run_number": 142
            },
            {
              "id": 26430887613,
              "status": "completed",
              "conclusion": "success",
              "created_at": "2026-05-26T03:40:42Z",
              "updated_at": "2026-05-26T03:52:12Z",
              "html_url": "https://github.com/RomanBazylev/hard4fun/actions/runs/26430887613",
              "run_number": 141
            }
          ]
        }
      },
      "video_stats": {
        "total": 200,
        "last_30d": 200,
        "avg_views": 1,
        "avg_likes": 0,
        "avg_comments": 0,
        "best_video": {
          "title": "Birds buffering mid-flight like a bad stream",
          "video_id": "vQ3wELnpiJ8",
          "views": 21
        },
        "last_upload": {
          "title": "Mirror shows you from 5 seconds in the future",
          "video_id": "2L7jBSjS54w",
          "uploaded_at": "2026-05-28T03:55:17.609732+00:00"
        },
        "last_short": null,
        "last_long": {
          "title": "Mirror shows you from 5 seconds in the future",
          "video_id": "2L7jBSjS54w",
          "uploaded_at": "2026-05-28T03:55:17.609732+00:00"
        }
      }
    }
  ]
}